nhs_waiting_lists/__init__.py
nhs_waiting_lists/callbacks.py
nhs_waiting_lists/constants.py
nhs_waiting_lists/run_cli.py
nhs_waiting_lists/commands/__init__.py
nhs_waiting_lists/commands/importer.py
nhs_waiting_lists/commands/provider.py
nhs_waiting_lists/commands/scraper.py
nhs_waiting_lists/config/__init__.py
nhs_waiting_lists/config/app_config.py
nhs_waiting_lists/core/__init__.py
nhs_waiting_lists/core/nhs_ctl_core.py
nhs_waiting_lists/core/waiting_list_db.py
nhs_waiting_lists/importer/__init__.py
nhs_waiting_lists/importer/outpatient_activity.py
nhs_waiting_lists/importer/providers.py
nhs_waiting_lists/importer/rtt.py
nhs_waiting_lists/importer/rtt_metrics.py
nhs_waiting_lists/importer/rtt_pathways.py
nhs_waiting_lists/importer/rtt_qa.py
nhs_waiting_lists/models/__init__.py
nhs_waiting_lists/models/admitted.py
nhs_waiting_lists/models/all_rtt_raw.py
nhs_waiting_lists/models/base.py
nhs_waiting_lists/models/consolidated.py
nhs_waiting_lists/models/incomplete.py
nhs_waiting_lists/models/new_periods.py
nhs_waiting_lists/models/nonadmitted.py
nhs_waiting_lists/models/outpatients_activity.py
nhs_waiting_lists/models/provider.py
nhs_waiting_lists/models/t_v_acute_trusts.py
nhs_waiting_lists/models/t_v_consolidated.py
nhs_waiting_lists/models/t_v_providers.py
nhs_waiting_lists/scraper/README.md
nhs_waiting_lists/scraper/__init__.py
nhs_waiting_lists/scraper/items.py
nhs_waiting_lists/scraper/pipelines.py
nhs_waiting_lists/scraper/settings.py
nhs_waiting_lists/scraper/samples/detail.html
nhs_waiting_lists/scraper/samples/hospital_outpatient_activity.html
nhs_waiting_lists/scraper/samples/main.html
nhs_waiting_lists/scraper/samples/outpatient_activity_index.html
nhs_waiting_lists/scraper/spiders/__init__.py
nhs_waiting_lists/scraper/spiders/outpatient_activity.py
nhs_waiting_lists/scraper/spiders/provider_oversight.py
nhs_waiting_lists/scraper/spiders/rtt_waiting_times.py
nhs_waiting_lists/utils/__init__.py
nhs_waiting_lists/utils/barcharts.py
nhs_waiting_lists-0.1.2.dist-info/METADATA
nhs_waiting_lists-0.1.2.dist-info/WHEEL
nhs_waiting_lists-0.1.2.dist-info/entry_points.txt
nhs_waiting_lists-0.1.2.dist-info/RECORD
