Metadata-Version: 2.4
Name: nhs-waiting-lists
Version: 0.1.2
Summary: This is a simple wrapper for working with the NHS referral-to-treatment dataset.
Author-email: Tom Hodder <tom@limepepper.co.uk>
Requires-Python: >=3.11
Requires-Dist: alembic>=1.17.0
Requires-Dist: bs4>=0.0.2
Requires-Dist: great-tables>=0.20.0
Requires-Dist: ipython-sql>=0.5.0
Requires-Dist: jupyterlab-night>=0.5.2
Requires-Dist: lifelines>=0.30.0
Requires-Dist: matplotlib>=3.10.7
Requires-Dist: notebook>=7.4.7
Requires-Dist: pandas-datareader>=0.10.0
Requires-Dist: pandas>=2.3.3
Requires-Dist: plotly>=6.5.0
Requires-Dist: plotnine>=0.15.0
Requires-Dist: pydantic-settings>=2.11.0
Requires-Dist: reportlab>=4.4.5
Requires-Dist: scrapy>=2.13.3
Requires-Dist: seaborn>=0.13.2
Requires-Dist: sqlalchemy>=2.0.44
Requires-Dist: typer==0.20.0
